odoo9_addon_partner_contact_nationality-9.0.1.0.0.99.dev29-py2.7-nspkg.pth
odoo9_addon_partner_contact_nationality-9.0.1.0.0.99.dev29.dist-info/DESCRIPTION.rst
odoo9_addon_partner_contact_nationality-9.0.1.0.0.99.dev29.dist-info/METADATA
odoo9_addon_partner_contact_nationality-9.0.1.0.0.99.dev29.dist-info/RECORD
odoo9_addon_partner_contact_nationality-9.0.1.0.0.99.dev29.dist-info/WHEEL
odoo9_addon_partner_contact_nationality-9.0.1.0.0.99.dev29.dist-info/metadata.json
odoo9_addon_partner_contact_nationality-9.0.1.0.0.99.dev29.dist-info/namespace_packages.txt
odoo9_addon_partner_contact_nationality-9.0.1.0.0.99.dev29.dist-info/top_level.txt
odoo_addons/partner_contact_nationality/README.rst
odoo_addons/partner_contact_nationality/__init__.py
odoo_addons/partner_contact_nationality/__openerp__.py
odoo_addons/partner_contact_nationality/i18n/am.po
odoo_addons/partner_contact_nationality/i18n/ar.po
odoo_addons/partner_contact_nationality/i18n/bg.po
odoo_addons/partner_contact_nationality/i18n/bs.po
odoo_addons/partner_contact_nationality/i18n/ca.po
odoo_addons/partner_contact_nationality/i18n/cs.po
odoo_addons/partner_contact_nationality/i18n/da.po
odoo_addons/partner_contact_nationality/i18n/de.po
odoo_addons/partner_contact_nationality/i18n/el_GR.po
odoo_addons/partner_contact_nationality/i18n/en_GB.po
odoo_addons/partner_contact_nationality/i18n/es.po
odoo_addons/partner_contact_nationality/i18n/es_CR.po
odoo_addons/partner_contact_nationality/i18n/es_EC.po
odoo_addons/partner_contact_nationality/i18n/es_MX.po
odoo_addons/partner_contact_nationality/i18n/es_VE.po
odoo_addons/partner_contact_nationality/i18n/et.po
odoo_addons/partner_contact_nationality/i18n/eu.po
odoo_addons/partner_contact_nationality/i18n/fi.po
odoo_addons/partner_contact_nationality/i18n/fr.po
odoo_addons/partner_contact_nationality/i18n/fr_CH.po
odoo_addons/partner_contact_nationality/i18n/gl.po
odoo_addons/partner_contact_nationality/i18n/hr.po
odoo_addons/partner_contact_nationality/i18n/hr_HR.po
odoo_addons/partner_contact_nationality/i18n/hu.po
odoo_addons/partner_contact_nationality/i18n/id.po
odoo_addons/partner_contact_nationality/i18n/it.po
odoo_addons/partner_contact_nationality/i18n/ja.po
odoo_addons/partner_contact_nationality/i18n/lt.po
odoo_addons/partner_contact_nationality/i18n/lv.po
odoo_addons/partner_contact_nationality/i18n/mk.po
odoo_addons/partner_contact_nationality/i18n/mn.po
odoo_addons/partner_contact_nationality/i18n/nb.po
odoo_addons/partner_contact_nationality/i18n/nb_NO.po
